LICENSE
MANIFEST.in
README.rst
VERSION
requirements-dev.txt
requirements.txt
setup.cfg
setup.py
azurekit/__init__.py
azurekit/manager.py
azurekit.egg-info/PKG-INFO
azurekit.egg-info/SOURCES.txt
azurekit.egg-info/dependency_links.txt
azurekit.egg-info/requires.txt
azurekit.egg-info/top_level.txt
azurekit/services/__init__.py
azurekit/services/base.py
azurekit/services/compute.py
test/__init__.py
test/factory.py
test/test_service_compute.py