Metadata-Version: 1.1
Name: azurekit
Version: 0.0.1
Summary: Azurekit is a Python SDK for managing your Azure accounts and all deployed resources. This way you can see, for example, all Ubuntu 16.06 machines deployed in your accounts.
Home-page: https://github.com/davidmoremad
Author: David Amrani Hernandez
Author-email: davidmorenomad@gmail.com
License: Apache 2.0
Project-URL: Source Code, https://github.com/davidmoremad/azurekit
Project-URL: Documentation, https://azurekit.readthedocs.io
Keywords: azure microsoft cloud platform sdk wrapper security management
Platform: UNKNOWN
Classifier: Development Status :: 4 - Beta
Classifier: Intended Audience :: Developers
Classifier: Intended Audience :: System Administrators
Classifier: Intended Audience :: Information Technology
Classifier: Intended Audience :: Other Audience
Classifier: License :: OSI Approved :: Apache Software License
Classifier: Natural Language :: English
Classifier: Operating System :: OS Independent
Classifier: Programming Language :: Python :: 2
Classifier: Programming Language :: Python :: 2.7
Classifier: Programming Language :: Python :: 3
Classifier: Programming Language :: Python :: 3.4
Classifier: Programming Language :: Python :: 3.5
Classifier: Programming Language :: Python :: 3.6
Classifier: Topic :: Software Development :: Libraries :: Python Modules
Classifier: Topic :: System :: Monitoring
Classifier: Topic :: System :: Networking
Classifier: Topic :: System :: Systems Administration
